lazy_signals-0.2.0.dist-info/licenses/LICENCE.md
lazysignals/__init__.py
lazysignals/_signals.py
lazysignals/_utils.py
lazy_signals-0.2.0.dist-info/METADATA
lazy_signals-0.2.0.dist-info/WHEEL
lazy_signals-0.2.0.dist-info/top_level.txt
lazy_signals-0.2.0.dist-info/RECORD
