Metadata-Version: 2.4
Name: lazy-signals
Version: 0.2.0
Summary: running effects on value updates with dependency discovery - conceptually inspired by Signal in JavaScript
Author-email: Adrian Gallus <mail@agallus.de>
License-Expression: MIT
Project-URL: Documentation, https://adrian-gallus.github.io/lazy-signals-python/
Project-URL: Repository, https://github.com/adrian-gallus/lazy-signals-python
Project-URL: Changelog, https://adrian-gallus.github.io/lazy-signals-python/changelog.html
Project-URL: Issues, https://github.com/adrian-gallus/lazy-signals-python/issues
Keywords: reactive,signals,effects,lazy,dependencies
Classifier: Intended Audience :: Developers
Classifier: Operating System :: OS Independent
Classifier: Programming Language :: Python :: 3
Classifier: Programming Language :: Python :: 3.6
Classifier: Programming Language :: Python :: 3.7
Classifier: Programming Language :: Python :: 3.8
Classifier: Programming Language :: Python :: 3.9
Classifier: Programming Language :: Python :: 3.10
Classifier: Programming Language :: Python :: 3.11
Classifier: Programming Language :: Python :: 3.12
Classifier: Programming Language :: Python :: 3.13
Classifier: Topic :: Software Development
Classifier: Topic :: Software Development :: Libraries
Classifier: Topic :: Software Development :: Libraries :: Python Modules
Classifier: Topic :: Utilities
Requires-Python: >=3.6
License-File: LICENCE.md
Dynamic: license-file
